{
	"class" : {
		"delete" : "jigyasagrover 6/24/2015 23:19",
		"instance" : "jigyasagrover 6/24/2015 23:18",
		"open" : "JigyasaGrover 6/26/2015 12:43",
		"restart" : "jigyasagrover 6/14/2015 14:06",
		"run" : "jigyasagrover 6/24/2015 23:22" },
	"instance" : {
		"Old_printSearchResults" : "jigyasa 8/12/2015 01:14",
		"backButtonClicked" : "jig 7/22/2015 13:51:19",
		"box" : "JigyasaGrover 6/30/2015 14:44",
		"box:" : "JigyasaGrover 6/30/2015 14:44",
		"builder" : "jigyasa 7/8/2015 14:16",
		"builder:" : "jigyasa 7/8/2015 14:16",
		"delete" : "jigyasagrover 6/24/2015 23:08",
		"dialog" : "jig 7/22/2015 13:51:19",
		"dialog:" : "jig 7/22/2015 13:51:19",
		"fileContents" : "JigyasaGrover 6/30/2015 19:37",
		"fileContents:" : "JigyasaGrover 6/30/2015 19:37",
		"initialize" : "jigyasa 8/12/2015 22:46",
		"myString" : "JigyasaGrover 6/26/2015 12:00",
		"myString:" : "JigyasaGrover 6/26/2015 12:47",
		"oldInitialize" : "jigyasa 7/23/2015 12:28",
		"open" : "JigyasaGrover 6/26/2015 12:44",
		"openAndPrint" : "jigyasagrover 7/2/2015 12:31",
		"printContent:" : "jigyasagrover 7/1/2015 15:27",
		"printSearchResults" : "Anonymous 8/19/2015 16:13",
		"searchResults" : "jigyasagrover 7/1/2015 13:17",
		"searchResults:" : "jigyasagrover 7/1/2015 13:17",
		"searchView" : "jigyasagrover 7/1/2015 15:16",
		"searchView:" : "jigyasagrover 7/1/2015 15:16",
		"viewer" : "jigyasagrover 7/1/2015 12:27",
		"viewer:" : "jigyasagrover 7/1/2015 12:27" } }
